Metadata-Version: 2.1
Name: lineintf
Version: 1.0.2
Summary: LineIntf - Line Interface makes easy to do tkinter interfaces placing the widgets in line styles.
Home-page: http://github.com/pointel-com-br/lineintf
Author: Pointel.com.br
Author-email: master@pointel.com.br
License: MIT
Platform: UNKNOWN
